README.rst
setup.py
smartencoding/__init__.py
smartencoding/six.py
smartencoding/tests.py
smartencoding.egg-info/PKG-INFO
smartencoding.egg-info/SOURCES.txt
smartencoding.egg-info/dependency_links.txt
smartencoding.egg-info/not-zip-safe
smartencoding.egg-info/requires.txt
smartencoding.egg-info/top_level.txt