Metadata-Version: 1.1
Name: smartencoding
Version: 0.3
Summary: Python smart encoding (smart_unicode and other functions)
Home-page: http://github.com/adw0rd/smartencoding
Author: Mikhail Andreev
Author-email: x11org@gmail.com
License: BSD
Keywords: smart_unicode,smart_text,smart_encode,smart,encoding,unicode
Platform: UNKNOWN
Classifier: Environment :: Web Environment
Classifier: Programming Language :: Python
Classifier: License :: OSI Approved :: BSD License
Classifier: Topic :: Software Development :: Libraries :: Python Modules
